b24api/__init__.py
b24api/async_api.py
b24api/base_api.py
b24api/entity.py
b24api/error.py
b24api/query.py
b24api/settings.py
b24api/sync_api.py
b24api/type.py
b24api-0.7.4.dist-info/licenses/LICENSE
b24api-0.7.4.dist-info/METADATA
b24api-0.7.4.dist-info/WHEEL
b24api-0.7.4.dist-info/top_level.txt
b24api-0.7.4.dist-info/RECORD
