Metadata-Version: 2.4
Name: b24api
Version: 0.7.4
Summary: Bitrix24 API
Requires-Python: >=3.12
License-File: LICENSE
Requires-Dist: aioitertools>=0.12.0
Requires-Dist: fast-depends>=2.4.12
Requires-Dist: httpx[http2]>=0.28.1
Requires-Dist: pydantic>=2.11.7
Requires-Dist: pydantic-settings>=2.10.1
Requires-Dist: pytest-asyncio>=1.1.0
Requires-Dist: tenacity>=9.1.2
Dynamic: license-file
